README.rst
setup.py
ext_sort/__about__.py
ext_sort/__init__.py
ext_sort/__main__.py
ext_sort/sort.py
ext_sort.egg-info/PKG-INFO
ext_sort.egg-info/SOURCES.txt
ext_sort.egg-info/dependency_links.txt
ext_sort.egg-info/entry_points.txt
ext_sort.egg-info/top_level.txt
tests/__init__.py
tests/conftest.py
tests/test_sort.py