Metadata-Version: 1.2
Name: ext-sort
Version: 0.2.0
Summary: External sort algorithm implementation.
Home-page: https://github.com/dapper91/python-external-sort
Author: Dmitry Pershin
Author-email: dapper91@mail.ru
License: Public Domain License
Keywords: python3,sort,external-sort,algorithms
Platform: UNKNOWN
Classifier: Development Status :: 4 - Beta
Classifier: Intended Audience :: Developers
Classifier: Natural Language :: English
Classifier: License :: Public Domain
Classifier: Programming Language :: Python
Classifier: Programming Language :: Python :: 3.6
Classifier: Programming Language :: Python :: 3.7
Requires-Python: >=3.6
